raccoon/__init__.py
raccoon/_version.py
raccoon/classification.py
raccoon/clustering.py
raccoon/interface.py
raccoon/main.py
raccoon/update.py
raccoon/optim/__init__.py
raccoon/optim/de.py
raccoon/optim/tpe.py
raccoon/utils/__init__.py
raccoon/utils/classes.py
raccoon/utils/functions.py
raccoon/utils/option.py
raccoon/utils/plots.py
raccoon/utils/trees.py
raccoon_cluster-0.5.1.dist-info/LICENSE
raccoon_cluster-0.5.1.dist-info/METADATA
raccoon_cluster-0.5.1.dist-info/WHEEL
raccoon_cluster-0.5.1.dist-info/top_level.txt
raccoon_cluster-0.5.1.dist-info/RECORD
