Metadata-Version: 2.1
Name: raccoon-cluster
Version: 0.5.1
Summary: Scale-adaptive clustering in Python
Home-page: https://github.com/shlienlab/raccoon
Download-URL: https://github.com/shlienlab/raccoon/archive/0.5.1.tar.gz
Author: Federico Comitani
Author-email: federico.comitani@gmail.com
License: GPL-3.0
Keywords: clustering,optimization,dimensionality-reduction,differential-evolution,knn,umap,hierarchical-clustering,multi-scale,scale-adaptive,optimal-clusters
Classifier: Development Status :: 4 - Beta
Classifier: Intended Audience :: Science/Research
Classifier: Topic :: Scientific/Engineering
Classifier: License :: OSI Approved :: GNU General Public License v3 (GPLv3)
Classifier: Programming Language :: Python
Classifier: Programming Language :: Python :: 3.7
Classifier: Programming Language :: Python :: 3.8
License-File: LICENSE
Requires-Dist: numpy (>=1.19.5)
Requires-Dist: pandas (>=1.1.3)
Requires-Dist: scikit-learn (>=0.22.2.post1)
Requires-Dist: scikit-network (==0.20.0)
Requires-Dist: numba (>=0.52.0)
Requires-Dist: umap-learn (>=0.3.9)
Requires-Dist: optuna (>=2.10.0)
Requires-Dist: psutil (>=5.7.3)
Requires-Dist: anytree (>=2.8.0)
Requires-Dist: matplotlib (>=3.3.3)
Requires-Dist: seaborn (>=0.11.0)
Provides-Extra: gpu
Requires-Dist: cupy (==8.60) ; extra == 'gpu'
Requires-Dist: cuml (==0.18) ; extra == 'gpu'
Requires-Dist: cudf (==0.18) ; extra == 'gpu'
Requires-Dist: cugraph (==0.18) ; extra == 'gpu'
Provides-Extra: hdbscan
Requires-Dist: hdbscan ; extra == 'hdbscan'
